<font>
	<info face="C:\Users\Administrator\Desktop\13465789-export" size="120" />
	<common lineHeight="120" scaleW="328" scaleH="387" pages="1" />
	<pages>
		<page id="0" file="C:\Users\Administrator\Desktop\13465789-export.png" />
	</pages>
	<chars count="13">
		<char id="49" x="82" y="258" width="81" height="128" xoffset="0" yoffset="-8" xadvance="65" /><!-- 1 -->
		<char id="50" x="246" y="0" width="81" height="128" xoffset="0" yoffset="-8" xadvance="65" /><!-- 2 -->
		<char id="51" x="164" y="258" width="81" height="128" xoffset="0" yoffset="-8" xadvance="65" /><!-- 3 -->
		<char id="52" x="164" y="129" width="81" height="128" xoffset="0" yoffset="-8" xadvance="65" /><!-- 4 -->
		<char id="53" x="164" y="0" width="81" height="128" xoffset="0" yoffset="-8" xadvance="65" /><!-- 5 -->
		<char id="54" x="246" y="129" width="81" height="128" xoffset="0" yoffset="-8" xadvance="65" /><!-- 6 -->
		<char id="55" x="82" y="129" width="81" height="128" xoffset="0" yoffset="-8" xadvance="65" /><!-- 7 -->
		<char id="56" x="82" y="0" width="81" height="128" xoffset="0" yoffset="-8" xadvance="65" /><!-- 8 -->
		<char id="57" x="0" y="258" width="81" height="128" xoffset="0" yoffset="-8" xadvance="65" /><!-- 9 -->
		<char id="48" x="0" y="129" width="81" height="128" xoffset="0" yoffset="-8" xadvance="65" /><!-- 0 -->
		<char id="44" x="0" y="0" width="81" height="128" xoffset="0" yoffset="-8" xadvance="65" /><!-- , -->
		<char id="32" x="0" y="0" width="0" height="0" xoffset="0" yoffset="0" xadvance="20" /><!--   -->
		<char id="9" x="0" y="0" width="0" height="0" xoffset="0" yoffset="0" xadvance="160" /><!-- 	 -->
	</chars>
	<kernings count="0">
	</kernings>
</font>